knewkarma/__init__.py
knewkarma/cli/__init__.py
knewkarma/cli/commands.py
knewkarma/cli/main.py
knewkarma/core/__init__.py
knewkarma/core/client.py
knewkarma/core/post.py
knewkarma/core/posts.py
knewkarma/core/search.py
knewkarma/core/shared.py
knewkarma/core/subreddit.py
knewkarma/core/subreddits.py
knewkarma/core/user.py
knewkarma/core/users.py
knewkarma/meta/__init__.py
knewkarma/meta/about.py
knewkarma/meta/license.py
knewkarma/meta/version.py
knewkarma-7.2.1.dist-info/METADATA
knewkarma-7.2.1.dist-info/WHEEL
knewkarma-7.2.1.dist-info/entry_points.txt
knewkarma-7.2.1.dist-info/licenses/LICENSE
knewkarma-7.2.1.dist-info/RECORD
