Metadata-Version: 2.4
Name: knewkarma
Version: 7.2.1
Summary: Reddit-data analysis toolkit
License: GPL-3.0+
License-File: LICENSE
Keywords: reddit,data-analysis
Author: Ritchie Mwewa
Author-email: rly0nheart@duck.com
Requires-Python: >=3.11,<4.0
Classifier: Development Status :: 5 - Production/Stable
Classifier: Intended Audience :: Developers
Classifier: Intended Audience :: Education
Classifier: License :: OSI Approved :: GNU General Public License v3 or later (GPLv3+)
Classifier: Natural Language :: English
Classifier: Operating System :: OS Independent
Classifier: Programming Language :: Python :: 3
Classifier: Programming Language :: Python :: 3.11
Classifier: Programming Language :: Python :: 3.12
Classifier: Programming Language :: Python :: 3.13
Classifier: Programming Language :: Python :: 3.14
Requires-Dist: pandas (>=2.1.4,<3.0.0)
Requires-Dist: praw (>=7.7.1,<8.0.0)
Requires-Dist: pydantic (>=2.11.5,<3.0.0)
Requires-Dist: requests (>=2.32.3,<3.0.0)
Requires-Dist: rich-click (>=1.8.9,<2.0.0)
Project-URL: issues, https://codeberg.org/rly0nheart/knewkarma/issues
Project-URL: repository, https://codeberg.org/rly0nheart/knewkarma
